ssb_libtest40/__init__.py
ssb_libtest40/__main__.py
ssb_libtest40/functions.py
ssb_libtest40/py.typed
ssb_libtest40-0.0.1.dist-info/LICENSE
ssb_libtest40-0.0.1.dist-info/METADATA
ssb_libtest40-0.0.1.dist-info/WHEEL
ssb_libtest40-0.0.1.dist-info/entry_points.txt
ssb_libtest40-0.0.1.dist-info/RECORD
